lvis/__init__.py
lvis/colormap.py
lvis/eval.py
lvis/lvis.py
lvis/results.py
lvis/vis.py
visaionlvis-0.5.4.dist-info/licenses/LICENSE
visaionlvis-0.5.4.dist-info/METADATA
visaionlvis-0.5.4.dist-info/WHEEL
visaionlvis-0.5.4.dist-info/top_level.txt
visaionlvis-0.5.4.dist-info/RECORD
