Metadata-Version: 2.4
Name: visaionlvis
Version: 0.5.4
Summary: Python API for LVIS dataset.
Author: Agrim Gupta
License-File: LICENSE
Requires-Dist: cycler>=0.10.0
Requires-Dist: Cython>=0.29.12
Requires-Dist: kiwisolver>=1.1.0
Requires-Dist: matplotlib>=3.1.1
Requires-Dist: numpy>=1.18.2
Requires-Dist: opencv-python>=4.1.0.25
Requires-Dist: pyparsing>=2.4.0
Requires-Dist: python-dateutil>=2.8.0
Requires-Dist: six>=1.12.0
Dynamic: author
Dynamic: description
Dynamic: description-content-type
Dynamic: license-file
Dynamic: requires-dist
Dynamic: summary
